{
  "display": {
    "icon": {
      "item": "minecraft:stone"
    },
    "title": {
      "translate": "advancements.gargoyles.root.title"
    },
    "description": {
      "translate": "advancements.gargoyles.root.desc"
    },
    "background": "minecraft:textures/blocks/cobblestone.png"
  },
    "criteria": {
        "star": {
            "trigger": "minecraft:inventory_changed",
            "conditions": {
                "items": [
                    {
                        "item": "gargoyles:stoneperch"
                    }
                ]
            }
        }
    }
}